LICENSE.txt
README.txt
setup.py
main/__init__.py
papermanagementsystem.egg-info/PKG-INFO
papermanagementsystem.egg-info/SOURCES.txt
papermanagementsystem.egg-info/dependency_links.txt
papermanagementsystem.egg-info/top_level.txt