Metadata-Version: 2.1
Name: papermanagementsystem
Version: 0.0.1
Summary: A very basic store management software
Home-page: 
Author: Akshat Kala
Author-email: itzakshat706@gmail.ccom
License: MIT
Keywords: store_management_software
Classifier: Development Status :: 5 - Production/Stable
Classifier: Intended Audience :: Education
Classifier: Operating System :: OS Independent
Classifier: License :: OSI Approved :: MIT License
Classifier: Programming Language :: Python :: 3
License-File: LICENSE.txt
